leader_clustering.py
leader_clustering-2.0.0.dist-info/LICENSE
leader_clustering-2.0.0.dist-info/METADATA
leader_clustering-2.0.0.dist-info/WHEEL
leader_clustering-2.0.0.dist-info/top_level.txt
leader_clustering-2.0.0.dist-info/RECORD
