Metadata-Version: 2.1
Name: leader-clustering
Version: 2.0.0
Summary: Leader algorithm for unsupervised clustering
Author: Pritish Banerjee and Amit Singh
Classifier: Programming Language :: Python :: 3
Classifier: License :: OSI Approved :: MIT License
Classifier: Operating System :: OS Independent
Requires-Python: >=3.6
License-File: LICENSE
